.travis.yml
AUTHORS
ChangeLog
LICENSE
README.md
setup.cfg
setup.py
tox.ini
pykins/__init__.py
pykins.egg-info/PKG-INFO
pykins.egg-info/SOURCES.txt
pykins.egg-info/dependency_links.txt
pykins.egg-info/entry_points.txt
pykins.egg-info/not-zip-safe
pykins.egg-info/pbr.json
pykins.egg-info/top_level.txt