Metadata-Version: 1.1
Name: pykins
Version: 0.1.0
Summary: Python API and CLI for Jenkins
Home-page: UNKNOWN
Author: Arie Bregman
Author-email: bregman.arie@gmail.com
License: Apache License, Version 2.0
Platform: UNKNOWN
Classifier: Topic :: Utilities
Classifier: Environment :: Console
Classifier: Intended Audience :: Developers
Classifier: Intended Audience :: Information Technology
Classifier: Intended Audience :: System Administrators
Classifier: License :: OSI Approved :: Apache Software License
Classifier: Operating System :: OS Independent
Classifier: Programming Language :: Python
Classifier: Programming Language :: Python :: 2
Classifier: Programming Language :: Python :: 2.7
